Sources/Defines.v
`ifndef OPCODES
    `define LOAD        7'b00_000_11
    `define LOAD_FP     7'b00_001_11
    `define custom_0    7'b00_010_11
    `define MISC_MEM    7'b00_011_11
    `define OP_IMM      7'b00_100_11
    `define AUIPC       7'b00_101_11
    `define OP_IMM_32   7'b00_110_11

    `define STORE       7'b01_000_11
    `define STORE_FP    7'b01_001_11
    `define custom_1    7'b01_010_11
    `define AMO         7'b01_011_11
    `define OP          7'b01_100_11
    `define LUI         7'b01_101_11
    `define OP_32       7'b01_110_11

    `define MADD        7'b10_000_11
    `define MSUB        7'b10_001_11
    `define NMSUB       7'b10_010_11
    `define NMADD       7'b10_011_11
    `define OP_FP       7'b10_100_11
    `define custom_2    7'b10_110_11

    `define BRANCH      7'b11_000_11
    `define JALR        7'b11_001_11
    `define JAL         7'b11_011_11
    `define SYSTEM      7'b11_100_11
    `define custom_3    7'b11_110_11
`endif /*OPCODES*/

`ifndef INSTRUCTION_TYPES
    `define R_TYPE 0
    `define I_TYPE 1
    `define S_TYPE 2
    `define B_TYPE 3
    `define U_TYPE 4
    `define J_TYPE 5
`endif /*INSTRUCTION_TYPES*/

`ifndef I_INSTRUCTIONS
    `define ADDI    3'b000
    `define SLTI    3'b010
    `define SLTIU   3'b011
    `define XORI    3'b100
    `define ORI     3'b110
    `define ANDI    3'b111
    `define SLLI    3'b001      // Shift Left Immediate -> Logical
    `define SRI     3'b101      // Shift Right Immediate -> Logical & Arithmetic
`endif /*I_INSTRUCTIONS*/

`ifndef R_INSTRUCTIONS
    `define ADDSUB  3'b000
    `define SLL     3'b001      // Shift Left -> Logical   
    `define SLT     3'b010
    `define SLTU    3'b011    
    `define XOR     3'b100    
    `define SR      3'b101      // Shift Right -> Logical & Arithmetic   
    `define OR      3'b110    
    `define AND     3'b111

    `define ADD     7'b0000000
    `define SUB     7'b0100000
`endif /*R_INSTRUCTIONS*/

`ifndef MUL_DIV_INSTRCUTIONS
    `define MUL     3'b000
    `define MULH    3'b001
    `define MULHSU  3'b010
    `define MULHU   3'b011 

    `define DIV     3'b100
    `define DIVU    3'b101
    `define REM     3'b110
    `define REMU    3'b111

    `define MULDIV  7'b0000001
`endif /*MUL_DIV_INSTRCUTIONS*/

`ifndef BRANCH_INSTRUCTIONS
    `define BEQ  3'b000
    `define BNE  3'b001
    `define BLT  3'b100
    `define BGE  3'b101
    `define BLTU 3'b110
    `define BGEU 3'b111
`endif /*BRANCH_INSTRUCTIONS*/

`ifndef ALU_OPERATIONS
    `define ALU_ADD     3'b000
    `define ALU_SUB     3'b001
    `define ALU_AND     3'b010
    `define ALU_OR      3'b011
    `define ALU_XOR     3'b100
`endif /*ALU_OPERATIONS*/

`ifndef ALU_SRC_SELECT
    `define PC          2'b00
    `define A           2'b01
    `define ALU_RESULT  2'b10

    `define B           2'b00
    `define FOUR        2'b01
    `define IMMEDIATE   2'b10
`endif /*ALU_SRC_SELECT*/

`ifndef REGISTER_FILE_WRITE_SOURCE
    `define MEMORY      2'b00
    `define ALU         2'b01
    `define MULTIPLIER  2'b10
`endif /*REGISTER_FILE_WRITE_SOURCE*/

`ifndef CONTROL_SIGNALS
    `define INSTRUCTION     1'b0
    `define DATA            1'b1

    `define READ            1'b0
    `define WRITE           1'b1

    `define DISABLE         1'b0
    `define ENABLE          1'b1
`endif /*CONTROL_SIGNALS*/

`ifndef CONTROLLER_STATES
    `define RESET            0
    `define FETCH_BEGIN      1
    `define FETCH_WAIT       2
    `define FETCH_DONE       3
    `define DECODE           4
    `define EXECUTE          5
    `define EXECUTE_BRANCH   6
    `define TAKE_BRANCH      7
`endif /*CONTROLLER_STATES*/

Sources/Multiplier.v
`include "Defines.v"

module Multiplier
(
    input enable,
    input [31 : 0] operand_1,
    input [31 : 0] operand_2,
    output reg [31 : 0] product
);

   //signal for encoder
    reg [3:0] neg;
    reg [3:0] one;
    reg [3:0] two;

    //description of partial products
    //partial products for 4 rows
    reg [15:0] pp0;
    reg [15:0] pp1;
    reg [15:0] pp2;
    reg [15:0] pp3;

    // // partial products array
    reg [7:0]p;

    // carry array
    reg [2:0]c;

    reg [7:0] operand_1_c;

     // represent bits of the operand_1 during the multiplication process used in signaling
    reg aj;
    reg aj_1;

    integer i ;
    integer j ;
    // // negative flag
    reg ng;

    reg [15:0]result;
    // carry save
    reg [7:0]c_save;

     // sign bit flag
      reg s;
   
    //negated values  

    reg naj;
    reg naj_1;
   

    always @(*)
    begin

        if(enable==1) begin
            i = 0;
            j = 0;
            c_save = 8'b0;

            // make signals values
            one[0] = ~(operand_2[2*0]^0);
            two[0]= ~(( operand_2[2*0+1] & ~operand_2[2*0] & (~0)  ) | ( (~operand_2[2*0+1]) & (operand_2[2*0]) & 0 ) );
            neg[0] = ((~(0))|(~(operand_2[2*0])))&(operand_2[2*0+1]);
            c[0] = neg[0] & ( ~operand_1[0] | one[0]);
                
            one[1] = ~(operand_2[2*1]^operand_2[2*1-1]);
            two[1]= ~(( operand_2[2*1+1] & ~operand_2[2*1] & (~operand_2[2*1-1])  ) | ( (~operand_2[2*1+1]) & (operand_2[2*1]) & operand_2[2*1-1] ) );
            neg[1] = ((~(operand_2[2*1-1]))|(~(operand_2[2*1])))&(operand_2[2*1+1]);
            c[1] = neg[1] & ( ~operand_1[0] | one[1]);

            one[2] = ~(operand_2[2*2]^operand_2[2*2-1]);
            two[2]= ~(( operand_2[2*2+1] & ~operand_2[2*2] & (~operand_2[2*2-1])  ) | ( (~operand_2[2*2+1]) & (operand_2[2*2]) & operand_2[2*2-1] ) );
            neg[2] = ((~(operand_2[2*2-1]))|(~(operand_2[2*2])))&(operand_2[2*2+1]);
            c[2] = neg[2] & ( ~operand_1[0] | one[2]);


            one[3] = ~(operand_2[2*3]^operand_2[2*3-1]);
            two[3]= ~(( operand_2[2*3+1] & ~operand_2[2*3] & (~operand_2[2*3-1])  ) | ( (~operand_2[2*3+1]) & (operand_2[2*3]) & operand_2[2*3-1] ) );
            neg[3] = ((~(operand_2[2*3-1]))|(~(operand_2[2*3])))&(operand_2[2*3+1]);



             // Computation of partial products for each 4-bit segment of operand_2

            for(i=0;i<=2;i++) begin
                
                for(j=0;j<=7;j++)begin 
                    if (j==0) begin
                        aj = operand_1[j];
                        aj_1 = 0;
                    end else begin
                        aj = operand_1[j];
                        aj_1 = operand_1[j-1];
                    end
                    naj_1 = ~((aj_1)^(neg[i]));
                    naj = ~((aj)^(neg[i]));
                    p[j] = ~(((two[i])|(naj_1))&((one[i])|(naj)));
                    if(j==7) begin
                        s = ~naj & (~one[i] | ~two[i]);
                    end
                end

                p[0] = ~(one[i]) & operand_1[0];
                
                 // determine partial products
                case (i) //[i][15:0]
                    0 : pp0 = {5'b0, ~s ,s ,s , p[7] ,p[6],p[5],p[4],p[3],p[2],p[1],p[0] };  
                    1 : pp1 = {4'b0,1'b1 ,~s , p[7] ,p[6],p[5],p[4],p[3],p[2],p[1],p[0] , c[i-1],1'b0 };
                    2 : pp2 = {2'b0 ,  1'b1 ,~s , p[7] ,p[6],p[5],p[4],p[3],p[2],p[1],p[0] , c[i-1],1'b0,1'b0,1'b0 };
                endcase
            end
                // Computation of carry-save based on operand_1
                for(i=0;i<=3;i++) begin
                    if(operand_1[2*i]==1'b1)begin
                        c_save[2*i] = 1;
                        c_save[2*i+1] = 1;
                    end else begin
                        if(operand_1[2*i]==1'b1) begin
                            c_save[2*i] = 0;
                            c_save[2*i+1] = 1;
                        end else begin
                            c_save[2*i] = 0;
                            c_save[2*i+1] = 0;
                        end
                    end
                end

                // Computation of carry-propagate for carry save
                for(i=0;i<=1;i++) begin
                    if(c_save[4*i+1]==1)begin
                        c_save[4*i+2] =1;
                        c_save[4*i+2] =1;
                    end
                end

                 // Set higher bits of carry_save if needed
                if(c_save[3]==1) begin
                    c_save[4]=1;
                    c_save[5]=1;
                    c_save[6]=1;
                    c_save[7]=1;
                end

                // Compute operand_1_carry  based on carry_save and operand_1
                ng = 0;
                for (i=0;i<=7;i++) begin
                    if(ng==1'b1) begin
                        operand_1_c[i] = ~operand_1[i];
                    end else begin
                        operand_1_c[i] = operand_1[i];
                    end
                    if(c_save[i]==1'b1) begin
                        ng = 1;
                    end
                end


            // Compute pp3 based on operand_1_carry 
            if(neg[3]==1'b1) begin
                neg[3]=0;
                for(j=0;j<=7;j++)begin 
                    if (j==0) begin
                        aj = operand_1_c[j];
                        aj_1 = 0;
                    end else begin
                        aj = operand_1_c[j];
                        aj_1 = operand_1_c[j-1];
                    end
                    p[j] = ~( (  (two[3])|(~((aj_1)^(neg[3])))  )&(   (one[3])|(~((aj)^(neg[3])))  ) );
                end


                pp3 = {  1'b1 ,~p[7] , p[7] ,p[6],p[5],p[4],p[3],p[2],p[1],p[0] , c[2],1'b0,1'b0,1'b0 ,1'b0,1'b0};          
            
            end else begin
                for(j=0;j<=7;j++)begin 
                    if (j==0) begin
                        aj = operand_1[j];
                        aj_1 = 0;
                    end else begin
                        aj = operand_1[j];
                        aj_1 = operand_1[j-1];
                    end
                    p[j] = ~( (  (two[3])|(~((aj_1)^(neg[3])))  )&(   (one[3])|(~((aj)^(neg[3])))  ) );
                end

                p[0] = ~(one[3]) & operand_1[0];
                pp3 = {  1'b1 ,~p[7] , p[7] ,p[6],p[5],p[4],p[3],p[2],p[1],p[0] , c[2],1'b0,1'b0,1'b0 ,1'b0,1'b0};                 
            end

            // Final addition of partial products to get the result
            result = pp0 + pp1 + pp2 + pp3;

           // Set the output product and make second 16 bit to zero
            product = {{16{result[15]}},result};
            end
    end 
    

    // Start your 8-bit multiplier design here
endmodule

Sources/multiplier_TestBench.v
`timescale 1ns/1ns
`include "Multiplier.v"

module multiplier_TestBench;

    parameter check_num = 10;
    reg [31:0] operand_1; 
    reg [31:0] operand_2;
    // wire [31:0] product;
    reg [7:0] var_1 ;
    reg [7:0] var_2;
    reg enable = 1;

    integer i = 0;


    // Instantiate the Multiplier module
    Multiplier uut (
        .operand_1(operand_1),
        .operand_2(operand_2),
        .enable(enable)
        //.product(product)

    );

    initial begin
      $dumpfile("Multiplier.vcd");
      $dumpvars(0,multiplier_TestBench);
        for (i=0;i<check_num;i++) 
        begin
           var_1 = $random;
           var_2  =$random;
            operand_1 =var_1; 
            operand_2 =var_2; 
            #1;

            //operand_1= -30;
            //operand_2= 20;
            //#1
        end

    end
    // // Stimulus generation
    // initial begin
    //     $dumpfile("Multiplier.vcd");
    //     $dumpvars(0,multiplier_TestBench);

    //     // Initialize inputs
    //     enable = 1;
    //     operand_1 = 8'b11001100; // Example input values
    //     operand_2 = 8'b10101010;

    //     #10 enable = 0; // Disable multiplier after 10 time units
    //     #10 enable = 1; // Re-enable multiplier
    //     #10 operand_1 = 8'b11110000; // Change input values
    //     #10 operand_2 = 8'b01010101;


    //     #100 $finish; // Stop simulation after 100 time units
    // end

    // Display results
    //   always @*
    //     $display("Result: %b", product);

endmodule

Sources/Multiplier.vcd
$date
	Fri Jan 19 18:17:56 2024
$end
$version
	Icarus Verilog
$end
$timescale
	1ns
$end
$scope module multiplier_TestBench $end
$var parameter 32 ! check_num $end
$var reg 1 " enable $end
$var reg 32 # operand_1 [31:0] $end
$var reg 32 $ operand_2 [31:0] $end
$var reg 8 % var_1 [7:0] $end
$var reg 8 & var_2 [7:0] $end
$var integer 32 ' i [31:0] $end
$scope module uut $end
$var wire 1 " enable $end
$var wire 32 ( operand_1 [31:0] $end
$var wire 32 ) operand_2 [31:0] $end
$var reg 1 * aj $end
$var reg 1 + aj_1 $end
$var reg 3 , c [2:0] $end
$var reg 8 - c_save [7:0] $end
$var reg 1 . naj $end
$var reg 1 / naj_1 $end
$var reg 4 0 neg [3:0] $end
$var reg 1 1 ng $end
$var reg 4 2 one [3:0] $end
$var reg 8 3 operand_1_c [7:0] $end
$var reg 8 4 p [7:0] $end
$var reg 16 5 pp0 [15:0] $end
$var reg 16 6 pp1 [15:0] $end
$var reg 16 7 pp2 [15:0] $end
$var reg 16 8 pp3 [15:0] $end
$var reg 32 9 product [31:0] $end
$var reg 16 : result [15:0] $end
$var reg 1 ; s $end
$var reg 4 < two [3:0] $end
$var integer 32 = i [31:0] $end
$var integer 32 > j [31:0] $end
$upscope $end
$upscope $end
$enddefinitions $end
$comment Show the parameter values. $end
$dumpall
b1010 !
$end
#0
$dumpvars
b1000 >
b1000 =
b111 <
0;
b1110111000100100 :
b11111111111111111110111000100100 9
b1010111000000000 8
b11000000000000 7
b110000000000 6
b10000100100 5
b10111000 4
b11011100 3
b1110 2
11
b0 0
1/
1.
b11111100 -
b0 ,
1+
1*
b10000001 )
b100100 (
b0 '
b10000001 &
b100100 %
b10000001 $
b100100 #
1"
$end
#1
b1101111011 9
b1101111011 :
b1100010010100000 8
b11110111 3
11
b10111011000000 7
b110000100100 6
b1111110111 5
1;
b10010 4
0.
0*
0/
0+
b100 ,
b11 <
b1100 2
b101 0
b111 -
b1000 >
b1000 =
b1100011 $
b1100011 )
b1001 #
b1001 (
b1100011 &
b1001 %
b1 '
#2
b11111111111111111111101000101001 9
b1111101000101001 :
b1011100110000000 8
b11110011 3
11
b11000011010000 7
b101111001100 6
b10000001101 5
0;
1.
1+
b11100110 4
1/
1*
b0 ,
b111 <
b1000 2
b10 0
b11111111 -
b1000 >
b1000 =
b10001101 $
b10001101 )
b1101 #
b1101 (
b10001101 &
b1101 %
b10 '
#3
b11100011010 9
b11100011010 :
b1100000000000000 8
b10011011 3
11
b11011001010000 7
b110110010110 6
b1100110100 5
0;
1.
0*
b0 4
0/
1+
b1 ,
b1 0
b1110 <
b1001 2
b11111111 -
b1000 >
b1000 =
b10010 $
b10010 )
b1100101 #
b1100101 (
b10010 &
b1100101 %
b11 '
#4
b1101 9
b1101 :
b11111111 3
11
b11000000010000 7
b101111111100 6
0;
b10000000001 5
b0 4
1.
1/
0+
0*
b0 ,
b10 0
b1111 <
b1000 2
b111 -
b1000 >
b1000 =
b1101 $
b1101 )
b1 #
b1 (
b1101 &
b1 %
b100 '
#5
b1110000011110 9
b1110000011110 :
b1101110110000000 8
b10001110 3
11
b11000000001000 7
b101000100000 6
0;
b10001110110 5
0/
1+
b1110110 4
1.
0*
b100 2
b10 ,
b11111100 -
b1000 >
b1000 =
b111101 $
b111101 )
b1110110 #
b1110110 (
b111101 &
b1110110 %
b101 '
#6
b100010011100 9
b100010011100 :
b1100100110000000 8
b10011 3
11
b10111011010000 7
1;
b110001001100 6
b10000000000 5
b100110 4
0.
0/
0+
0*
b10 0
b111 <
b0 ,
b1001 2
b11111111 -
b1000 >
b1000 =
b10001100 $
b10001100 )
b11101101 #
b11101101 (
b10001100 &
b11101101 %
b110 '
#7
b110010110 9
b110010110 :
b1100000111000000 8
b111 3
11
b11000000000000 7
b101111001010 6
b10000001100 5
0;
0/
0+
b111 4
0.
0*
b111 2
b1 ,
b1 0
b1100 <
b11110111 -
b1000 >
b1000 =
b11000110 $
b11000110 )
b11111001 #
b11111001 (
b11000110 &
b11111001 %
b111 '
#8
b1001111010010 9
b1001111010010 :
b1100111011000000 8
b111011 3
11
b11001110110000 7
b110011101110 6
b10001110100 5
b111011 4
1/
0+
1.
0*
b111 0
b1110 <
b1 2
b11111111 -
b1000 >
b1000 =
b10101010 $
b10101010 )
b11000101 #
b11000101 (
b10101010 &
b11000101 %
b1000 '
#9
b11111111111111111111001101110011 9
b1111001101110011 :
b1011001010000000 8
b11011 3
11
b11000110110000 7
b101100101000 6
0;
b10000011011 5
1.
1+
b11001010 4
1/
1*
b101 0
b0 ,
b101 <
b1010 2
b11111111 -
b1000 >
b1000 =
b1110111 $
b1110111 )
b11100101 #
b11100101 (
b1110111 &
b11100101 %
b1001 '
#10
b1010 '
